bencode2/__bencode.pyi
bencode2/__decoder.py
bencode2/__encoder.py
bencode2/__init__.py
bencode2/__init__.pyi
bencode2/bencode.cpp
bencode2/common.hpp
bencode2/decode.cpp
bencode2/encode.cpp
bencode2/encode_ctx.hpp
bencode2/overflow.hpp
bencode2/py.typed
bencode2-0.3.29.dist-info/licenses/LICENSE
bencode2-0.3.29.dist-info/WHEEL
bencode2-0.3.29.dist-info/METADATA
bencode2-0.3.29.dist-info/RECORD
