Metadata-Version: 2.4
Name: bencode2
Version: 0.3.29
Summary: A fast and correct bencode serialize/deserialize library
Keywords: bencode,bittorrent,bit-torrent,serialize,deserialize,p2p
Author-email: trim21 <trim21me@gmail.com>
Requires-Python: >=3.10
Classifier: Development Status :: 5 - Production/Stable
Classifier: License :: OSI Approved :: MIT License
Classifier: Operating System :: OS Independent
Classifier: Programming Language :: Python
Classifier: Programming Language :: Python :: 3 :: Only
License-File: LICENSE
Requires-Dist: typing_extensions>=4.8.0
Project-URL: Homepage, https://github.com/trim21/bencode-py
Project-URL: Issues, https://github.com/trim21/bencode-py/issues
Project-URL: Repository, https://github.com/trim21/bencode-py
